{
  "schema_version": 2,
  "id": "onebot_api",
  "latest_version": "1.0.0",
  "etag": "\"9943ce8e807bcf51221acd6194391f3d6d61a6c6ad4144f73c2af717b3d6cdb6\"",
  "releases": [
    {
      "url": "https://github.com/HuajiMUR233/OneBotAPI/releases/tag/1.0.0",
      "name": "1.0.0",
      "tag_name": "1.0.0",
      "created_at": "2021-09-02T11:46:12Z",
      "assets": [
        {
          "name": "OneBotAPI-v1.0.0.mcdr",
          "size": 15163,
          "download_count": 35,
          "created_at": "2021-09-02T14:37:05Z",
          "browser_download_url": "https://github.com/HuajiMUR233/OneBotAPI/releases/download/1.0.0/OneBotAPI-v1.0.0.mcdr"
        }
      ],
      "description": "",
      "prerelease": false,
      "parsed_version": "1.0.0"
    }
  ]
}