{
  "schema_version": 2,
  "id": "lazytp",
  "latest_version": "2.0.1",
  "etag": "\"ad09113458267c0f44970f96ea12b9105d465d3cb5678f14699c9f7282dfeac5\"",
  "releases": [
    {
      "url": "https://github.com/Lazy-Bing-Server/lazytp/releases/tag/2.0.1",
      "name": "2.0.1",
      "tag_name": "2.0.1",
      "created_at": "2021-08-27T16:12:37Z",
      "assets": [
        {
          "name": "LazyTeleport-v2.0.1.mcdr",
          "size": 20019,
          "download_count": 214,
          "created_at": "2021-08-27T16:14:43Z",
          "browser_download_url": "https://github.com/Lazy-Bing-Server/lazytp/releases/download/2.0.1/LazyTeleport-v2.0.1.mcdr"
        }
      ],
      "description": "Metadata fixes, License included in MCDR file",
      "prerelease": false,
      "parsed_version": "2.0.1"
    },
    {
      "url": "https://github.com/Lazy-Bing-Server/lazytp/releases/tag/2.0.0",
      "name": "2.0.0 for MCDR 2.1+",
      "tag_name": "2.0.0",
      "created_at": "2021-08-27T15:59:55Z",
      "assets": [
        {
          "name": "LazyTeleport-v2.0.0.mcdr",
          "size": 7561,
          "download_count": 224,
          "created_at": "2021-08-27T16:04:24Z",
          "browser_download_url": "https://github.com/Lazy-Bing-Server/lazytp/releases/download/2.0.0/LazyTeleport-v2.0.0.mcdr"
        }
      ],
      "description": "first release",
      "prerelease": false,
      "parsed_version": "2.0.0"
    }
  ]
}