{
  "schema_version": 2,
  "id": "timed_quick_backup_multi",
  "latest_version": "1.0.1",
  "etag": "\"f9ef05a42ad4e345650de1f2b93166084e5dc08817be13ec9093de7aa6df421a\"",
  "releases": [
    {
      "url": "https://github.com/TISUnion/TimedQBM/releases/tag/v1.0.1",
      "name": "",
      "tag_name": "v1.0.1",
      "created_at": "2021-08-16T03:49:16Z",
      "assets": [
        {
          "name": "TimedQBM-v1.0.1.mcdr",
          "size": 16435,
          "download_count": 123,
          "created_at": "2021-08-16T17:10:01Z",
          "browser_download_url": "https://github.com/TISUnion/TimedQBM/releases/download/v1.0.1/TimedQBM-v1.0.1.mcdr"
        }
      ],
      "description": "",
      "prerelease": false,
      "parsed_version": "1.0.1"
    }
  ]
}