{
  "schema_version": 2,
  "id": "info",
  "latest_version": "0.0.2",
  "etag": "\"78bfe68efe0ca2413d9112734bcee906af29265abb09fb0a5394e04ab6297c69\"",
  "releases": [
    {
      "url": "https://github.com/zhang-anzhi/MCDReforgedPlugins/releases/tag/info-v0.0.2",
      "name": "Info-v0.0.2",
      "tag_name": "info-v0.0.2",
      "created_at": "2021-08-22T16:30:59Z",
      "assets": [
        {
          "name": "Info-v0.0.2.mcdr",
          "size": 2177,
          "download_count": 787,
          "created_at": "2021-08-22T16:42:48Z",
          "browser_download_url": "https://github.com/zhang-anzhi/MCDReforgedPlugins/releases/download/info-v0.0.2/Info-v0.0.2.mcdr"
        }
      ],
      "description": "",
      "prerelease": false,
      "parsed_version": "0.0.2"
    }
  ]
}