{
  "schema_version": 2,
  "id": "mc_uuid",
  "latest_version": "1.0.0",
  "etag": "\"6403faf96b29165a2fa0b7ec83db0be47d5eba581e336f9b685393486f159923\"",
  "releases": [
    {
      "url": "https://github.com/HuajiMUR233/MCUUID/releases/tag/1.0.0",
      "name": "\\1.0.0/",
      "tag_name": "1.0.0",
      "created_at": "2021-08-16T15:50:52Z",
      "assets": [
        {
          "name": "MinecraftUUIDAPI-v1.0.0.mcdr",
          "size": 1891,
          "download_count": 247,
          "created_at": "2021-08-16T15:53:02Z",
          "browser_download_url": "https://github.com/HuajiMUR233/MCUUID/releases/download/1.0.0/MinecraftUUIDAPI-v1.0.0.mcdr"
        }
      ],
      "description": "",
      "prerelease": false,
      "parsed_version": "1.0.0"
    }
  ]
}