{
  "schema_version": 2,
  "id": "run_some_commands",
  "latest_version": "1.0.0",
  "etag": "\"920912fa77169701a287930d6bdc314ae6c5e35706a8721dcb350b7e95abedf1\"",
  "releases": [
    {
      "url": "https://github.com/FlyingShuriken/MCDR-plugins/releases/tag/v1.0.0",
      "name": "RSM v1.0.0",
      "tag_name": "v1.0.0",
      "created_at": "2021-08-20T10:41:28Z",
      "assets": [
        {
          "name": "run_some_commands_v1.0.0.mcdr",
          "size": 2768,
          "download_count": 17,
          "created_at": "2021-08-20T14:56:00Z",
          "browser_download_url": "https://github.com/FlyingShuriken/MCDR-plugins/releases/download/v1.0.0/run_some_commands_v1.0.0.mcdr"
        }
      ],
      "description": "",
      "prerelease": false,
      "parsed_version": "1.0.0"
    }
  ]
}